__init__.py
seleasium.py
seleasium_dirtydan-0.0.1.dist-info/LICENSE
seleasium_dirtydan-0.0.1.dist-info/METADATA
seleasium_dirtydan-0.0.1.dist-info/WHEEL
seleasium_dirtydan-0.0.1.dist-info/top_level.txt
seleasium_dirtydan-0.0.1.dist-info/RECORD
