Metadata-Version: 2.1
Name: seleasium-dirtydan
Version: 0.0.1
Summary: Basically just a class with methods that make selenium a bit easier.
Author-email: Taylor Rodieck <tw.rodieck@gmail.com>
Project-URL: Homepage, https://github.com/TaylorRodieck/seleasium
Classifier: Development Status :: 1 - Planning
Classifier: Programming Language :: Python :: 3
Classifier: License :: OSI Approved :: Apache Software License
Classifier: Operating System :: OS Independent
Requires-Python: >=3.7
License-File: LICENSE
